<?xml version="1.0" encoding="UTF-8"?>
<metadata xml:lang="zh"><Esri><CreaDate>20150924</CreaDate><CreaTime>22042000</CreaTime><ArcGISFormat>1.0</ArcGISFormat><SyncOnce>TRUE</SyncOnce><DataProperties><lineage><Process ToolSource="c:\program files (x86)\arcgis\desktop10.2\ArcToolbox\Toolboxes\Data Management Tools.tbx\CalculateField" Date="20150414" Time="164013">CalculateField landowner farmerID [GRIDCODE] VB #</Process><Process ToolSource="C:\Program Files (x86)\ArcGIS\Desktop10.0\ArcToolbox\Toolboxes\Data Management Tools.tbx\AddField" Date="20150417" Time="183437">AddField landowner year2 SHORT # # # # NON_NULLABLE NON_REQUIRED #</Process><Process ToolSource="C:\Program Files (x86)\ArcGIS\Desktop10.0\ArcToolbox\Toolboxes\Data Management Tools.tbx\AddField" Date="20150417" Time="183447">AddField landowner year3 SHORT # # # # NON_NULLABLE NON_REQUIRED #</Process><Process ToolSource="C:\Program Files (x86)\ArcGIS\Desktop10.0\ArcToolbox\Toolboxes\Data Management Tools.tbx\AddField" Date="20150417" Time="183459">AddField landowner year4 SHORT # # # # NON_NULLABLE NON_REQUIRED #</Process><Process ToolSource="C:\Program Files (x86)\ArcGIS\Desktop10.0\ArcToolbox\Toolboxes\Data Management Tools.tbx\AddField" Date="20150417" Time="183511">AddField landowner year5 SHORT # # # # NON_NULLABLE NON_REQUIRED #</Process><Process ToolSource="C:\Program Files (x86)\ArcGIS\Desktop10.0\ArcToolbox\Toolboxes\Data Management Tools.tbx\CalculateField" Date="20150418" Time="225420">CalculateField landowner MJ "Int ( [MJ]/400 )*0.6" VB #</Process><Process ToolSource="C:\Program Files (x86)\ArcGIS\Desktop10.0\ArcToolbox\Toolboxes\Data Management Tools.tbx\CalculateField" Date="20150419" Time="195546">CalculateField landowner landuse [firstyear] VB #</Process><Process ToolSource="C:\Program Files (x86)\ArcGIS\Desktop10.0\ArcToolbox\Toolboxes\Data Management Tools.tbx\CalculateField" Date="20150419" Time="195615">CalculateField landowner landuse [yare1] VB #</Process><Process ToolSource="C:\Program Files (x86)\ArcGIS\Desktop10.0\ArcToolbox\Toolboxes\Data Management Tools.tbx\CalculateField" Date="20150419" Time="195649">CalculateField landowner landuse [year4] VB #</Process><Process ToolSource="C:\Program Files (x86)\ArcGIS\Desktop10.0\ArcToolbox\Toolboxes\Data Management Tools.tbx\CalculateField" Date="20150420" Time="172452">CalculateField landowner MJ "Int ( [MJ]/400 )*0.6" VB #</Process><Process ToolSource="C:\Program Files (x86)\ArcGIS\Desktop10.0\ArcToolbox\Toolboxes\Data Management Tools.tbx\CalculateField" Date="20150420" Time="172506">CalculateField landowner MJ "Int ( [MJ]/400 )*0.6" VB #</Process><Process ToolSource="C:\Program Files (x86)\ArcGIS\Desktop10.0\ArcToolbox\Toolboxes\Data Management Tools.tbx\CalculateField" Date="20150420" Time="172553">CalculateField landowner MJ "Int ( [MJ]/400 )*0.6" VB #</Process><Process ToolSource="C:\Program Files (x86)\ArcGIS\Desktop10.0\ArcToolbox\Toolboxes\Data Management Tools.tbx\AddField" Date="20150420" Time="173909">AddField landowner year6 SHORT 5 # # # NON_NULLABLE NON_REQUIRED #</Process><Process ToolSource="C:\Program Files (x86)\ArcGIS\Desktop10.0\ArcToolbox\Toolboxes\Data Management Tools.tbx\AddField" Date="20150420" Time="174021">AddField landowner year7 SHORT 5 # # # NON_NULLABLE NON_REQUIRED #</Process><Process ToolSource="C:\Program Files (x86)\ArcGIS\Desktop10.0\ArcToolbox\Toolboxes\Data Management Tools.tbx\AddField" Date="20150420" Time="174033">AddField landowner year8 SHORT 5 # # # NON_NULLABLE NON_REQUIRED #</Process><Process ToolSource="C:\Program Files (x86)\ArcGIS\Desktop10.0\ArcToolbox\Toolboxes\Data Management Tools.tbx\AddField" Date="20150420" Time="174044">AddField landowner year9 SHORT 5 # # # NON_NULLABLE NON_REQUIRED #</Process><Process ToolSource="C:\Program Files (x86)\ArcGIS\Desktop10.0\ArcToolbox\Toolboxes\Data Management Tools.tbx\AddField" Date="20150420" Time="174053">AddField landowner year10 SHORT 5 # # # NON_NULLABLE NON_REQUIRED #</Process><Process ToolSource="C:\Program Files (x86)\ArcGIS\Desktop10.0\ArcToolbox\Toolboxes\Data Management Tools.tbx\CalculateField" Date="20150420" Time="175557">CalculateField landowner MJ "Int ( [MJ]/400 )*0.6" VB #</Process><Process ToolSource="C:\Program Files (x86)\ArcGIS\Desktop10.0\ArcToolbox\Toolboxes\Data Management Tools.tbx\CalculateField" Date="20150420" Time="180428">CalculateField landowner MJ [MJ]/10000*15 VB #</Process><Process ToolSource="C:\Program Files (x86)\ArcGIS\Desktop10.0\ArcToolbox\Toolboxes\Data Management Tools.tbx\CalculateField" Date="20150420" Time="180607">CalculateField landowner MJ "Int ( [MJ]/0.6 )*0.6" VB #</Process><Process ToolSource="C:\Program Files (x86)\ArcGIS\Desktop10.0\ArcToolbox\Toolboxes\Data Management Tools.tbx\CalculateField" Date="20150420" Time="180852">CalculateField landowner MJ "Int ( [MJ]/400 )*0.6" VB #</Process><Process ToolSource="C:\Program Files (x86)\ArcGIS\Desktop10.0\ArcToolbox\Toolboxes\Data Management Tools.tbx\CalculateField" Date="20150421" Time="100051">CalculateField landowner landuse [firstyear] VB #</Process><Process ToolSource="C:\Program Files (x86)\ArcGIS\Desktop10.0\ArcToolbox\Toolboxes\Data Management Tools.tbx\CalculateField" Date="20150421" Time="101007">CalculateField landowner landuse 1 VB #</Process><Process ToolSource="C:\Program Files (x86)\ArcGIS\Desktop10.0\ArcToolbox\Toolboxes\Data Management Tools.tbx\CalculateField" Date="20150421" Time="110300">CalculateField landowner landuse [year6] VB #</Process><Process ToolSource="D:\Program Files (x86)\ArcGIS\Desktop10.0\ArcToolbox\Toolboxes\Data Management Tools.tbx\CalculateField" Date="20151025" Time="194059">CalculateField landowner landuse [year9] VB #</Process><Process ToolSource="D:\Program Files (x86)\ArcGIS\Desktop10.0\ArcToolbox\Toolboxes\Data Management Tools.tbx\CalculateField" Date="20151026" Time="102412">CalculateField "intensity pattern" landuse [year3] VB #</Process><Process ToolSource="D:\Program Files (x86)\ArcGIS\Desktop10.0\ArcToolbox\Toolboxes\Data Management Tools.tbx\CalculateField" Date="20151026" Time="102547">CalculateField "intensity pattern" landuse [firstyear] VB #</Process><Process ToolSource="D:\Program Files (x86)\ArcGIS\Desktop10.0\ArcToolbox\Toolboxes\Data Management Tools.tbx\CalculateField" Date="20151026" Time="102818">CalculateField "intensity pattern" landuse [year3] VB #</Process><Process ToolSource="D:\Program Files (x86)\ArcGIS\Desktop10.0\ArcToolbox\Toolboxes\Data Management Tools.tbx\CalculateField" Date="20151026" Time="103107">CalculateField "intensity pattern" landuse [firstyear] VB #</Process><Process ToolSource="D:\Program Files (x86)\ArcGIS\Desktop10.0\ArcToolbox\Toolboxes\Data Management Tools.tbx\CalculateField" Date="20151026" Time="175545">CalculateField "intensity pattern" landuse [year3] VB #</Process><Process ToolSource="D:\Program Files (x86)\ArcGIS\Desktop10.0\ArcToolbox\Toolboxes\Data Management Tools.tbx\CalculateField" Date="20151026" Time="175706">CalculateField "intensity pattern" landuse [year8] VB #</Process><Process ToolSource="D:\Program Files (x86)\ArcGIS\Desktop10.0\ArcToolbox\Toolboxes\Data Management Tools.tbx\CalculateField" Date="20151026" Time="175745">CalculateField "intensity pattern" landuse [firstyear] VB #</Process><Process ToolSource="D:\Program Files (x86)\ArcGIS\Desktop10.0\ArcToolbox\Toolboxes\Data Management Tools.tbx\CalculateField" Date="20151026" Time="180008">CalculateField "intensity pattern" landuse [year3] VB #</Process><Process ToolSource="D:\Program Files (x86)\ArcGIS\Desktop10.0\ArcToolbox\Toolboxes\Data Management Tools.tbx\CalculateField" Date="20151026" Time="180039">CalculateField "intensity pattern" landuse [year8] VB #</Process><Process ToolSource="D:\Program Files (x86)\ArcGIS\Desktop10.0\ArcToolbox\Toolboxes\Data Management Tools.tbx\CalculateField" Date="20151026" Time="180850">CalculateField "intensity pattern" landuse [firstyear] VB #</Process><Process ToolSource="D:\Program Files (x86)\ArcGIS\Desktop10.0\ArcToolbox\Toolboxes\Data Management Tools.tbx\CalculateField" Date="20151026" Time="180918">CalculateField "intensity pattern" landuse [year3] VB #</Process><Process ToolSource="D:\Program Files (x86)\ArcGIS\Desktop10.0\ArcToolbox\Toolboxes\Data Management Tools.tbx\CalculateField" Date="20151104" Time="205756">CalculateField landowner pri 1 VB #</Process><Process ToolSource="D:\Program Files (x86)\ArcGIS\Desktop10.0\ArcToolbox\Toolboxes\Data Management Tools.tbx\CalculateField" Date="20151105" Time="161328">CalculateField "intensity pattern" firstyear 1 VB #</Process><Process ToolSource="D:\Program Files (x86)\ArcGIS\Desktop10.0\ArcToolbox\Toolboxes\Data Management Tools.tbx\CalculateField" Date="20151110" Time="162920">CalculateField "intensity pattern" landuse [firstyear] VB #</Process><Process ToolSource="D:\Program Files (x86)\ArcGIS\Desktop10.0\ArcToolbox\Toolboxes\Data Management Tools.tbx\CalculateField" Date="20151110" Time="171202">CalculateField "intensity pattern" landuse [year8] VB #</Process><Process ToolSource="D:\Program Files (x86)\ArcGIS\Desktop10.0\ArcToolbox\Toolboxes\Data Management Tools.tbx\CalculateField" Date="20151110" Time="172044">CalculateField "intensity pattern" landuse [firstyear] VB #</Process><Process ToolSource="D:\Program Files (x86)\ArcGIS\Desktop10.0\ArcToolbox\Toolboxes\Data Management Tools.tbx\CalculateField" Date="20151110" Time="235147">CalculateField "intensity pattern" landuse [firstyear] VB #</Process><Process ToolSource="D:\Program Files (x86)\ArcGIS\Desktop10.0\ArcToolbox\Toolboxes\Data Management Tools.tbx\CalculateField" Date="20151110" Time="235634">CalculateField "intensity pattern" landuse [year3] VB #</Process><Process ToolSource="D:\Program Files (x86)\ArcGIS\Desktop10.0\ArcToolbox\Toolboxes\Data Management Tools.tbx\CalculateField" Date="20151110" Time="235804">CalculateField "intensity pattern" landuse [year8] VB #</Process><Process ToolSource="D:\Program Files (x86)\ArcGIS\Desktop10.0\ArcToolbox\Toolboxes\Data Management Tools.tbx\CalculateField" Date="20151111" Time="000029">CalculateField "intensity pattern" landuse [firstyear] VB #</Process><Process ToolSource="D:\Program Files (x86)\ArcGIS\Desktop10.0\ArcToolbox\Toolboxes\Data Management Tools.tbx\CalculateField" Date="20151111" Time="000153">CalculateField "intensity pattern" landuse [year3] VB #</Process><Process ToolSource="D:\Program Files (x86)\ArcGIS\Desktop10.0\ArcToolbox\Toolboxes\Data Management Tools.tbx\CalculateField" Date="20151111" Time="001542">CalculateField "intensity pattern" landuse [firstyear] VB #</Process><Process ToolSource="D:\Program Files (x86)\ArcGIS\Desktop10.0\ArcToolbox\Toolboxes\Data Management Tools.tbx\CalculateField" Date="20151111" Time="001709">CalculateField "intensity pattern" landuse [year3] VB #</Process><Process ToolSource="D:\Program Files (x86)\ArcGIS\Desktop10.0\ArcToolbox\Toolboxes\Data Management Tools.tbx\CalculateField" Date="20151111" Time="001829">CalculateField "intensity pattern" landuse [year8] VB #</Process><Process ToolSource="D:\Program Files (x86)\ArcGIS\Desktop10.0\ArcToolbox\Toolboxes\Data Management Tools.tbx\CalculateField" Date="20151112" Time="123229">CalculateField "intensity patterns" landuse [year3] VB #</Process><Process ToolSource="D:\Program Files (x86)\ArcGIS\Desktop10.0\ArcToolbox\Toolboxes\Data Management Tools.tbx\CalculateField" Date="20151112" Time="123422">CalculateField "intensity patterns" landuse [year8] VB #</Process><Process ToolSource="D:\Program Files (x86)\ArcGIS\Desktop10.0\ArcToolbox\Toolboxes\Data Management Tools.tbx\CalculateField" Date="20151112" Time="123645">CalculateField "intensity patterns" landuse [firstyear] VB #</Process><Process ToolSource="D:\Program Files (x86)\ArcGIS\Desktop10.0\ArcToolbox\Toolboxes\Data Management Tools.tbx\CalculateField" Date="20151119" Time="154413">CalculateField "intensity patterns" landuse [firstyear] VB #</Process><Process ToolSource="D:\Program Files (x86)\ArcGIS\Desktop10.0\ArcToolbox\Toolboxes\Data Management Tools.tbx\CalculateField" Date="20151119" Time="154429">CalculateField "intensity patterns" landuse [year8] VB #</Process><Process ToolSource="D:\Program Files (x86)\ArcGIS\Desktop10.0\ArcToolbox\Toolboxes\Data Management Tools.tbx\CalculateField" Date="20151119" Time="154509">CalculateField "intensity patterns" landuse [firstyear] VB #</Process><Process ToolSource="D:\Program Files (x86)\ArcGIS\Desktop10.0\ArcToolbox\Toolboxes\Data Management Tools.tbx\CalculateField" Date="20151119" Time="154553">CalculateField "intensity patterns" landuse [year8] VB #</Process><Process ToolSource="D:\Program Files (x86)\ArcGIS\Desktop10.0\ArcToolbox\Toolboxes\Data Management Tools.tbx\CalculateField" Date="20151119" Time="154653">CalculateField "intensity patterns" landuse [firstyear] VB #</Process><Process ToolSource="D:\Program Files (x86)\ArcGIS\Desktop10.0\ArcToolbox\Toolboxes\Data Management Tools.tbx\CalculateField" Date="20151119" Time="154709">CalculateField "intensity patterns" landuse [year8] VB #</Process><Process ToolSource="D:\Program Files (x86)\ArcGIS\Desktop10.0\ArcToolbox\Toolboxes\Data Management Tools.tbx\CalculateField" Date="20151119" Time="154754">CalculateField "intensity patterns" landuse [firstyear] VB #</Process><Process ToolSource="D:\Program Files (x86)\ArcGIS\Desktop10.0\ArcToolbox\Toolboxes\Data Management Tools.tbx\CalculateField" Date="20151119" Time="155334">CalculateField "cultivation activity" landuse [year8] VB #</Process><Process ToolSource="D:\Program Files (x86)\ArcGIS\Desktop10.0\ArcToolbox\Toolboxes\Data Management Tools.tbx\CalculateField" Date="20151119" Time="155426">CalculateField "cultivation activity" landuse [firstyear] VB #</Process><Process ToolSource="D:\Program Files (x86)\ArcGIS\Desktop10.0\ArcToolbox\Toolboxes\Data Management Tools.tbx\CalculateField" Date="20151119" Time="155447">CalculateField "cultivation activity" landuse [year8] VB #</Process><Process ToolSource="D:\Program Files (x86)\ArcGIS\Desktop10.0\ArcToolbox\Toolboxes\Data Management Tools.tbx\CalculateField" Date="20151119" Time="155507">CalculateField "cultivation activity" landuse [firstyear] VB #</Process><Process ToolSource="D:\Program Files (x86)\ArcGIS\Desktop10.0\ArcToolbox\Toolboxes\Data Management Tools.tbx\CalculateField" Date="20151119" Time="155524">CalculateField "cultivation activity" landuse [year8] VB #</Process><Process ToolSource="D:\Program Files (x86)\ArcGIS\Desktop10.0\ArcToolbox\Toolboxes\Data Management Tools.tbx\CalculateField" Date="20151119" Time="155544">CalculateField "cultivation activity" landuse [firstyear] VB #</Process><Process ToolSource="D:\Program Files (x86)\ArcGIS\Desktop10.0\ArcToolbox\Toolboxes\Data Management Tools.tbx\CalculateField" Date="20151119" Time="181528">CalculateField "cultivation activity" landuse [firstyear] VB #</Process><Process ToolSource="D:\Program Files (x86)\ArcGIS\Desktop10.0\ArcToolbox\Toolboxes\Data Management Tools.tbx\CalculateField" Date="20151119" Time="182524">CalculateField "cultivation activity" landuse [year3] VB #</Process><Process ToolSource="D:\Program Files (x86)\ArcGIS\Desktop10.0\ArcToolbox\Toolboxes\Data Management Tools.tbx\CalculateField" Date="20151119" Time="182655">CalculateField "cultivation activity" landuse [year8] VB #</Process><Process ToolSource="D:\Program Files (x86)\ArcGIS\Desktop10.0\ArcToolbox\Toolboxes\Data Management Tools.tbx\CalculateField" Date="20151119" Time="183525">CalculateField "cultivation activity" landuse [firstyear] VB #</Process><Process ToolSource="D:\Program Files (x86)\ArcGIS\Desktop10.0\ArcToolbox\Toolboxes\Data Management Tools.tbx\CalculateField" Date="20151119" Time="183938">CalculateField "cultivation activity" landuse [year3] VB #</Process><Process ToolSource="D:\Program Files (x86)\ArcGIS\Desktop10.0\ArcToolbox\Toolboxes\Data Management Tools.tbx\CalculateField" Date="20151119" Time="184053">CalculateField "cultivation activity" landuse [year8] VB #</Process><Process ToolSource="D:\Program Files (x86)\ArcGIS\Desktop10.0\ArcToolbox\Toolboxes\Data Management Tools.tbx\AddField" Date="20161215" Time="212239">AddField landowner year1 SHORT # # # # NON_NULLABLE NON_REQUIRED #</Process><Process ToolSource="D:\Program Files (x86)\ArcGIS\Desktop10.0\ArcToolbox\Toolboxes\Data Management Tools.tbx\CalculateField" Date="20161215" Time="212258">CalculateField landowner year1 [yare1] VB #</Process><Process ToolSource="D:\Program Files (x86)\ArcGIS\Desktop10.0\ArcToolbox\Toolboxes\Data Management Tools.tbx\CalculateField" Date="20161219" Time="175204">CalculateField T landuse [firstyear] VB #</Process></lineage></DataProperties></Esri></metadata>
